[
  {
    "company_tag_id": 1,
    "company_tag_name": "1 年内",
    "company_tag_subdimension_name": "成立年限",
    "company_tag_auto_rule_type": "derived_rule",
    "rule_definition": {
      "version": 1,
      "tag_name": "1 年内",
      "subdimension_name": "成立年限",
      "exclusive_group": "age_established_range",
      "description": "成立未满 1 年",
      "logic": {
        "op": "age_years_range",
        "field": "establish_date",
        "min": 0,
        "max": 1
      }
    },
    "is_enabled": 1
  },
  {
    "company_tag_id": 2,
    "company_tag_name": "1-5 年",
    "company_tag_subdimension_name": "成立年限",
    "company_tag_auto_rule_type": "derived_rule",
    "rule_definition": {
      "version": 1,
      "tag_name": "1-5 年",
      "subdimension_name": "成立年限",
      "exclusive_group": "age_established_range",
      "description": "成立 1 至 5 年",
      "logic": {
        "op": "age_years_range",
        "field": "establish_date",
        "min": 1,
        "max": 5
      }
    },
    "is_enabled": 1
  },
  {
    "company_tag_id": 3,
    "company_tag_name": "5-10 年",
    "company_tag_subdimension_name": "成立年限",
    "company_tag_auto_rule_type": "derived_rule",
    "rule_definition": {
      "version": 1,
      "tag_name": "5-10 年",
      "subdimension_name": "成立年限",
      "exclusive_group": "age_established_range",
      "description": "成立 5 至 10 年",
      "logic": {
        "op": "age_years_range",
        "field": "establish_date",
        "min": 5,
        "max": 10
      }
    },
    "is_enabled": 1
  },
  {
    "company_tag_id": 4,
    "company_tag_name": "10-15 年",
    "company_tag_subdimension_name": "成立年限",
    "company_tag_auto_rule_type": "derived_rule",
    "rule_definition": {
      "version": 1,
      "tag_name": "10-15 年",
      "subdimension_name": "成立年限",
      "exclusive_group": "age_established_range",
      "description": "成立 10 至 15 年",
      "logic": {
        "op": "age_years_range",
        "field": "establish_date",
        "min": 10,
        "max": 15
      }
    },
    "is_enabled": 1
  },
  {
    "company_tag_id": 5,
    "company_tag_name": "15 年以上",
    "company_tag_subdimension_name": "成立年限",
    "company_tag_auto_rule_type": "derived_rule",
    "rule_definition": {
      "version": 1,
      "tag_name": "15 年以上",
      "subdimension_name": "成立年限",
      "exclusive_group": "age_established_range",
      "description": "成立 15 年及以上",
      "logic": {
        "op": "age_years_range",
        "field": "establish_date",
        "min": 15
      }
    },
    "is_enabled": 1
  },
  {
    "company_tag_id": 6,
    "company_tag_name": "注册资本:0 万-100 万",
    "company_tag_subdimension_name": "注册资本",
    "company_tag_auto_rule_type": "derived_rule",
    "rule_definition": {
      "version": 1,
      "tag_name": "注册资本:0 万-100 万",
      "subdimension_name": "注册资本",
      "exclusive_group": "register_capital_range",
      "description": "注册资本在 0 至 100 万之间",
      "logic": {
        "op": "numeric_range",
        "field": "register_capital",
        "min": 0,
        "max": 100
      }
    },
    "is_enabled": 1
  },
  {
    "company_tag_id": 7,
    "company_tag_name": "注册资本:100 万-200 万",
    "company_tag_subdimension_name": "注册资本",
    "company_tag_auto_rule_type": "derived_rule",
    "rule_definition": {
      "version": 1,
      "tag_name": "注册资本:100 万-200 万",
      "subdimension_name": "注册资本",
      "exclusive_group": "register_capital_range",
      "description": "注册资本在 100 至 200 万之间",
      "logic": {
        "op": "numeric_range",
        "field": "register_capital",
        "min": 100,
        "max": 200
      }
    },
    "is_enabled": 1
  },
  {
    "company_tag_id": 8,
    "company_tag_name": "200 万- 500 万",
    "company_tag_subdimension_name": "注册资本",
    "company_tag_auto_rule_type": "derived_rule",
    "rule_definition": {
      "version": 1,
      "tag_name": "200 万- 500 万",
      "subdimension_name": "注册资本",
      "exclusive_group": "register_capital_range",
      "description": "注册资本在 200 至 500 万之间",
      "logic": {
        "op": "numeric_range",
        "field": "register_capital",
        "min": 200,
        "max": 500
      }
    },
    "is_enabled": 1
  },
  {
    "company_tag_id": 9,
    "company_tag_name": "500 万- 1000 万",
    "company_tag_subdimension_name": "注册资本",
    "company_tag_auto_rule_type": "derived_rule",
    "rule_definition": {
      "version": 1,
      "tag_name": "500 万- 1000 万",
      "subdimension_name": "注册资本",
      "exclusive_group": "register_capital_range",
      "description": "注册资本在 500 至 1000 万之间",
      "logic": {
        "op": "numeric_range",
        "field": "register_capital",
        "min": 500,
        "max": 1000
      }
    },
    "is_enabled": 1
  },
  {
    "company_tag_id": 10,
    "company_tag_name": "1000 万以上",
    "company_tag_subdimension_name": "注册资本",
    "company_tag_auto_rule_type": "derived_rule",
    "rule_definition": {
      "version": 1,
      "tag_name": "1000 万以上",
      "subdimension_name": "注册资本",
      "exclusive_group": "register_capital_range",
      "description": "注册资本在 1000 万及以上",
      "logic": {
        "op": "numeric_range",
        "field": "register_capital",
        "min": 1000
      }
    },
    "is_enabled": 1
  },
  {
    "company_tag_id": 11,
    "company_tag_name": "有实缴资本",
    "company_tag_subdimension_name": "实缴资本",
    "company_tag_auto_rule_type": "derived_rule",
    "rule_definition": {
      "version": 1,
      "tag_name": "有实缴资本",
      "subdimension_name": "实缴资本",
      "exclusive_group": "paid_capital_presence",
      "description": "实缴资本大于 0",
      "logic": {
        "op": "numeric_compare",
        "field": "paid_capital",
        "gt": 0
      }
    },
    "is_enabled": 1
  },
  {
    "company_tag_id": 12,
    "company_tag_name": "无实缴资本",
    "company_tag_subdimension_name": "实缴资本",
    "company_tag_auto_rule_type": "derived_rule",
    "rule_definition": {
      "version": 1,
      "tag_name": "无实缴资本",
      "subdimension_name": "实缴资本",
      "exclusive_group": "paid_capital_presence",
      "description": "实缴资本为空或小于等于 0",
      "logic": {
        "op": "not",
        "rule": {
          "op": "numeric_compare",
          "field": "paid_capital",
          "gt": 0
        }
      }
    },
    "is_enabled": 1
  },
  {
    "company_tag_id": 13,
    "company_tag_name": "实缴资本:0 万-100 万",
    "company_tag_subdimension_name": "实缴资本",
    "company_tag_auto_rule_type": "derived_rule",
    "rule_definition": {
      "version": 1,
      "tag_name": "实缴资本:0 万-100 万",
      "subdimension_name": "实缴资本",
      "exclusive_group": "paid_capital_range",
      "description": "实缴资本在 0 至 100 万之间",
      "logic": {
        "op": "numeric_range",
        "field": "paid_capital",
        "min": 0,
        "max": 100
      }
    },
    "is_enabled": 1
  },
  {
    "company_tag_id": 14,
    "company_tag_name": "实缴资本:100 万-200 万",
    "company_tag_subdimension_name": "实缴资本",
    "company_tag_auto_rule_type": "derived_rule",
    "rule_definition": {
      "version": 1,
      "tag_name": "实缴资本:100 万-200 万",
      "subdimension_name": "实缴资本",
      "exclusive_group": "paid_capital_range",
      "description": "实缴资本在 100 至 200 万之间",
      "logic": {
        "op": "numeric_range",
        "field": "paid_capital",
        "min": 100,
        "max": 200
      }
    },
    "is_enabled": 1
  },
  {
    "company_tag_id": 15,
    "company_tag_name": "200 万-500 万",
    "company_tag_subdimension_name": "实缴资本",
    "company_tag_auto_rule_type": "derived_rule",
    "rule_definition": {
      "version": 1,
      "tag_name": "200 万-500 万",
      "subdimension_name": "实缴资本",
      "exclusive_group": "paid_capital_range",
      "description": "实缴资本在 200 至 500 万之间",
      "logic": {
        "op": "numeric_range",
        "field": "paid_capital",
        "min": 200,
        "max": 500
      }
    },
    "is_enabled": 1
  },
  {
    "company_tag_id": 16,
    "company_tag_name": "500 万-1000 万",
    "company_tag_subdimension_name": "实缴资本",
    "company_tag_auto_rule_type": "derived_rule",
    "rule_definition": {
      "version": 1,
      "tag_name": "500 万-1000 万",
      "subdimension_name": "实缴资本",
      "exclusive_group": "paid_capital_range",
      "description": "实缴资本在 500 至 1000 万之间",
      "logic": {
        "op": "numeric_range",
        "field": "paid_capital",
        "min": 500,
        "max": 1000
      }
    },
    "is_enabled": 1
  },
  {
    "company_tag_id": 17,
    "company_tag_name": "1000 万-5000 万",
    "company_tag_subdimension_name": "实缴资本",
    "company_tag_auto_rule_type": "derived_rule",
    "rule_definition": {
      "version": 1,
      "tag_name": "1000 万-5000 万",
      "subdimension_name": "实缴资本",
      "exclusive_group": "paid_capital_range",
      "description": "实缴资本在 1000 至 5000 万之间",
      "logic": {
        "op": "numeric_range",
        "field": "paid_capital",
        "min": 1000,
        "max": 5000
      }
    },
    "is_enabled": 1
  },
  {
    "company_tag_id": 18,
    "company_tag_name": "5000 万以上",
    "company_tag_subdimension_name": "实缴资本",
    "company_tag_auto_rule_type": "derived_rule",
    "rule_definition": {
      "version": 1,
      "tag_name": "5000 万以上",
      "subdimension_name": "实缴资本",
      "exclusive_group": "paid_capital_range",
      "description": "实缴资本在 5000 万及以上",
      "logic": {
        "op": "numeric_range",
        "field": "paid_capital",
        "min": 5000
      }
    },
    "is_enabled": 1
  },
  {
    "company_tag_id": 50,
    "company_tag_name": "有分支机构",
    "company_tag_subdimension_name": "分支机构数量",
    "company_tag_auto_rule_type": "direct_match",
    "rule_definition": {
      "version": 1,
      "tag_name": "有分支机构",
      "subdimension_name": "分支机构数量",
      "exclusive_group": "branch_presence",
      "description": "分支机构数量大于 0",
      "logic": {
        "op": "numeric_compare",
        "field": "branch_count",
        "gt": 0
      }
    },
    "is_enabled": 1
  },
  {
    "company_tag_id": 51,
    "company_tag_name": "无分支机构",
    "company_tag_subdimension_name": "分支机构数量",
    "company_tag_auto_rule_type": "direct_match",
    "rule_definition": {
      "version": 1,
      "tag_name": "无分支机构",
      "subdimension_name": "分支机构数量",
      "exclusive_group": "branch_presence",
      "description": "分支机构数量等于 0",
      "logic": {
        "op": "numeric_compare",
        "field": "branch_count",
        "eq": 0
      }
    },
    "is_enabled": 1
  },
  {
    "company_tag_id": 52,
    "company_tag_name": "有企业地址",
    "company_tag_subdimension_name": "地址信息",
    "company_tag_auto_rule_type": "direct_match",
    "rule_definition": {
      "version": 1,
      "tag_name": "有企业地址",
      "subdimension_name": "地址信息",
      "exclusive_group": "address_presence",
      "description": "存在注册地址或地址明细",
      "logic": {
        "op": "boolean_true",
        "field": "has_address"
      }
    },
    "is_enabled": 1
  },
  {
    "company_tag_id": 53,
    "company_tag_name": "无企业地址",
    "company_tag_subdimension_name": "地址信息",
    "company_tag_auto_rule_type": "direct_match",
    "rule_definition": {
      "version": 1,
      "tag_name": "无企业地址",
      "subdimension_name": "地址信息",
      "exclusive_group": "address_presence",
      "description": "不存在注册地址且无地址明细",
      "logic": {
        "op": "boolean_false",
        "field": "has_address"
      }
    },
    "is_enabled": 1
  },
  {
    "company_tag_id": 64,
    "company_tag_name": "员工人数:小于 50 人",
    "company_tag_subdimension_name": "员工人数",
    "company_tag_auto_rule_type": "derived_rule",
    "rule_definition": {
      "version": 1,
      "tag_name": "员工人数:小于 50 人",
      "subdimension_name": "员工人数",
      "exclusive_group": "employee_count_range",
      "description": "员工人数小于 50",
      "logic": {
        "op": "numeric_range",
        "field": "employee_count",
        "min": 0,
        "max": 50
      }
    },
    "is_enabled": 1
  },
  {
    "company_tag_id": 65,
    "company_tag_name": "员工人数:50-99 人",
    "company_tag_subdimension_name": "员工人数",
    "company_tag_auto_rule_type": "derived_rule",
    "rule_definition": {
      "version": 1,
      "tag_name": "员工人数:50-99 人",
      "subdimension_name": "员工人数",
      "exclusive_group": "employee_count_range",
      "description": "员工人数在 50 至 99",
      "logic": {
        "op": "numeric_range",
        "field": "employee_count",
        "min": 50,
        "max": 100
      }
    },
    "is_enabled": 1
  },
  {
    "company_tag_id": 66,
    "company_tag_name": "员工人数:100-499 人",
    "company_tag_subdimension_name": "员工人数",
    "company_tag_auto_rule_type": "derived_rule",
    "rule_definition": {
      "version": 1,
      "tag_name": "员工人数:100-499 人",
      "subdimension_name": "员工人数",
      "exclusive_group": "employee_count_range",
      "description": "员工人数在 100 至 499",
      "logic": {
        "op": "numeric_range",
        "field": "employee_count",
        "min": 100,
        "max": 500
      }
    },
    "is_enabled": 1
  },
  {
    "company_tag_id": 67,
    "company_tag_name": "员工人数:500 人以上",
    "company_tag_subdimension_name": "员工人数",
    "company_tag_auto_rule_type": "derived_rule",
    "rule_definition": {
      "version": 1,
      "tag_name": "员工人数:500 人以上",
      "subdimension_name": "员工人数",
      "exclusive_group": "employee_count_range",
      "description": "员工人数在 500 及以上",
      "logic": {
        "op": "numeric_range",
        "field": "employee_count",
        "min": 500
      }
    },
    "is_enabled": 1
  },
  {
    "company_tag_id": 68,
    "company_tag_name": "未披露",
    "company_tag_subdimension_name": "员工人数",
    "company_tag_auto_rule_type": "derived_rule",
    "rule_definition": {
      "version": 1,
      "tag_name": "未披露",
      "subdimension_name": "员工人数",
      "exclusive_group": "employee_count_range",
      "description": "员工人数未披露",
      "logic": {
        "op": "is_null",
        "field": "employee_count"
      }
    },
    "is_enabled": 1
  },
  {
    "company_tag_id": 69,
    "company_tag_name": "社保人数:小于 50 人",
    "company_tag_subdimension_name": "社保人数",
    "company_tag_auto_rule_type": "derived_rule",
    "rule_definition": {
      "version": 1,
      "tag_name": "社保人数:小于 50 人",
      "subdimension_name": "社保人数",
      "exclusive_group": "insured_count_range",
      "description": "社保人数小于 50",
      "logic": {
        "op": "numeric_range",
        "field": "insured_count",
        "min": 0,
        "max": 50
      }
    },
    "is_enabled": 1
  },
  {
    "company_tag_id": 70,
    "company_tag_name": "社保人数:50-99 人",
    "company_tag_subdimension_name": "社保人数",
    "company_tag_auto_rule_type": "derived_rule",
    "rule_definition": {
      "version": 1,
      "tag_name": "社保人数:50-99 人",
      "subdimension_name": "社保人数",
      "exclusive_group": "insured_count_range",
      "description": "社保人数在 50 至 99",
      "logic": {
        "op": "numeric_range",
        "field": "insured_count",
        "min": 50,
        "max": 100
      }
    },
    "is_enabled": 1
  },
  {
    "company_tag_id": 71,
    "company_tag_name": "社保人数:100-499 人",
    "company_tag_subdimension_name": "社保人数",
    "company_tag_auto_rule_type": "derived_rule",
    "rule_definition": {
      "version": 1,
      "tag_name": "社保人数:100-499 人",
      "subdimension_name": "社保人数",
      "exclusive_group": "insured_count_range",
      "description": "社保人数在 100 至 499",
      "logic": {
        "op": "numeric_range",
        "field": "insured_count",
        "min": 100,
        "max": 500
      }
    },
    "is_enabled": 1
  },
  {
    "company_tag_id": 72,
    "company_tag_name": "社保人数:500 人以上",
    "company_tag_subdimension_name": "社保人数",
    "company_tag_auto_rule_type": "derived_rule",
    "rule_definition": {
      "version": 1,
      "tag_name": "社保人数:500 人以上",
      "subdimension_name": "社保人数",
      "exclusive_group": "insured_count_range",
      "description": "社保人数在 500 及以上",
      "logic": {
        "op": "numeric_range",
        "field": "insured_count",
        "min": 500
      }
    },
    "is_enabled": 1
  },
  {
    "company_tag_id": 78,
    "company_tag_name": "有联系电话",
    "company_tag_subdimension_name": "联系方式",
    "company_tag_auto_rule_type": "derived_rule",
    "rule_definition": {
      "version": 1,
      "tag_name": "有联系电话",
      "subdimension_name": "联系方式",
      "exclusive_group": null,
      "description": "企业存在至少一个联系电话",
      "logic": {
        "op": "phone_any"
      }
    },
    "is_enabled": 1
  },
  {
    "company_tag_id": 79,
    "company_tag_name": "有固定电话",
    "company_tag_subdimension_name": "联系方式",
    "company_tag_auto_rule_type": "derived_rule",
    "rule_definition": {
      "version": 1,
      "tag_name": "有固定电话",
      "subdimension_name": "联系方式",
      "exclusive_group": null,
      "description": "联系电话中命中固定电话模式",
      "logic": {
        "op": "phone_regex",
        "pattern": "0[0-9]{2,3}-?[0-9]{7,8}"
      }
    },
    "is_enabled": 1
  },
  {
    "company_tag_id": 80,
    "company_tag_name": "有手机号",
    "company_tag_subdimension_name": "联系方式",
    "company_tag_auto_rule_type": "derived_rule",
    "rule_definition": {
      "version": 1,
      "tag_name": "有手机号",
      "subdimension_name": "联系方式",
      "exclusive_group": null,
      "description": "联系电话中命中手机号模式",
      "logic": {
        "op": "phone_regex",
        "pattern": "1[3-9][0-9]{9}"
      }
    },
    "is_enabled": 1
  },
  {
    "company_tag_id": 81,
    "company_tag_name": "有工商信息邮箱",
    "company_tag_subdimension_name": "工商信息邮箱",
    "company_tag_auto_rule_type": "direct_match",
    "rule_definition": {
      "version": 1,
      "tag_name": "有工商信息邮箱",
      "subdimension_name": "工商信息邮箱",
      "exclusive_group": "business_email_presence",
      "description": "工商邮箱非空",
      "logic": {
        "op": "non_empty",
        "field": "email_business"
      }
    },
    "is_enabled": 1
  },
  {
    "company_tag_id": 82,
    "company_tag_name": "无工商信息邮箱",
    "company_tag_subdimension_name": "工商信息邮箱",
    "company_tag_auto_rule_type": "direct_match",
    "rule_definition": {
      "version": 1,
      "tag_name": "无工商信息邮箱",
      "subdimension_name": "工商信息邮箱",
      "exclusive_group": "business_email_presence",
      "description": "工商邮箱为空",
      "logic": {
        "op": "is_empty",
        "field": "email_business"
      }
    },
    "is_enabled": 1
  },
  {
    "company_tag_id": 83,
    "company_tag_name": "是小微企业",
    "company_tag_subdimension_name": "小微企业",
    "company_tag_auto_rule_type": "direct_match",
    "rule_definition": {
      "version": 1,
      "tag_name": "是小微企业",
      "subdimension_name": "小微企业",
      "exclusive_group": "micro_enterprise",
      "description": "is_micro_enterprise = 1",
      "logic": {
        "op": "numeric_compare",
        "field": "is_micro_enterprise",
        "eq": 1
      }
    },
    "is_enabled": 1
  },
  {
    "company_tag_id": 84,
    "company_tag_name": "非小微企业",
    "company_tag_subdimension_name": "小微企业",
    "company_tag_auto_rule_type": "direct_match",
    "rule_definition": {
      "version": 1,
      "tag_name": "非小微企业",
      "subdimension_name": "小微企业",
      "exclusive_group": "micro_enterprise",
      "description": "is_micro_enterprise = 0",
      "logic": {
        "op": "numeric_compare",
        "field": "is_micro_enterprise",
        "eq": 0
      }
    },
    "is_enabled": 1
  },
  {
    "company_tag_id": 87,
    "company_tag_name": "一般纳税人",
    "company_tag_subdimension_name": "一般纳税人",
    "company_tag_auto_rule_type": "direct_match",
    "rule_definition": {
      "version": 1,
      "tag_name": "一般纳税人",
      "subdimension_name": "一般纳税人",
      "exclusive_group": "general_taxpayer",
      "description": "is_general_taxpayer = 1",
      "logic": {
        "op": "numeric_compare",
        "field": "is_general_taxpayer",
        "eq": 1
      }
    },
    "is_enabled": 1
  },
  {
    "company_tag_id": 88,
    "company_tag_name": "非一般纳税人",
    "company_tag_subdimension_name": "一般纳税人",
    "company_tag_auto_rule_type": "direct_match",
    "rule_definition": {
      "version": 1,
      "tag_name": "非一般纳税人",
      "subdimension_name": "一般纳税人",
      "exclusive_group": "general_taxpayer",
      "description": "is_general_taxpayer = 0",
      "logic": {
        "op": "numeric_compare",
        "field": "is_general_taxpayer",
        "eq": 0
      }
    },
    "is_enabled": 1
  },
  {
    "company_tag_id": 93,
    "company_tag_name": "有招聘",
    "company_tag_subdimension_name": "招聘信息",
    "company_tag_auto_rule_type": "direct_match",
    "rule_definition": {
      "version": 1,
      "tag_name": "有招聘",
      "subdimension_name": "招聘信息",
      "exclusive_group": "recruitment_presence",
      "description": "招聘布尔标记为 1 或招聘数量大于 0",
      "logic": {
        "op": "or",
        "rules": [
          {
            "op": "numeric_compare",
            "field": "has_recruitment",
            "eq": 1
          },
          {
            "op": "numeric_compare",
            "field": "recruit_count",
            "gt": 0
          }
        ]
      }
    },
    "is_enabled": 1
  },
  {
    "company_tag_id": 94,
    "company_tag_name": "无招聘",
    "company_tag_subdimension_name": "招聘信息",
    "company_tag_auto_rule_type": "direct_match",
    "rule_definition": {
      "version": 1,
      "tag_name": "无招聘",
      "subdimension_name": "招聘信息",
      "exclusive_group": "recruitment_presence",
      "description": "招聘布尔标记为 0 且招聘数量为 0",
      "logic": {
        "op": "and",
        "rules": [
          {
            "op": "numeric_compare",
            "field": "has_recruitment",
            "eq": 0
          },
          {
            "op": "numeric_compare",
            "field": "recruit_count",
            "eq": 0
          }
        ]
      }
    },
    "is_enabled": 1
  },
  {
    "company_tag_id": 132,
    "company_tag_name": "有专利",
    "company_tag_subdimension_name": "专利信息",
    "company_tag_auto_rule_type": "direct_match",
    "rule_definition": {
      "version": 1,
      "tag_name": "有专利",
      "subdimension_name": "专利信息",
      "exclusive_group": "patent_presence",
      "description": "专利布尔标记为 1 或专利数量大于 0",
      "logic": {
        "op": "or",
        "rules": [
          {
            "op": "numeric_compare",
            "field": "has_patent",
            "eq": 1
          },
          {
            "op": "numeric_compare",
            "field": "patent_count",
            "gt": 0
          }
        ]
      }
    },
    "is_enabled": 1
  },
  {
    "company_tag_id": 133,
    "company_tag_name": "无专利",
    "company_tag_subdimension_name": "专利信息",
    "company_tag_auto_rule_type": "direct_match",
    "rule_definition": {
      "version": 1,
      "tag_name": "无专利",
      "subdimension_name": "专利信息",
      "exclusive_group": "patent_presence",
      "description": "专利布尔标记为 0 且专利数量为 0",
      "logic": {
        "op": "and",
        "rules": [
          {
            "op": "numeric_compare",
            "field": "has_patent",
            "eq": 0
          },
          {
            "op": "numeric_compare",
            "field": "patent_count",
            "eq": 0
          }
        ]
      }
    },
    "is_enabled": 1
  },
  {
    "company_tag_id": 134,
    "company_tag_name": "有作品著作权",
    "company_tag_subdimension_name": "作品著作权",
    "company_tag_auto_rule_type": "direct_match",
    "rule_definition": {
      "version": 1,
      "tag_name": "有作品著作权",
      "subdimension_name": "作品著作权",
      "exclusive_group": "work_copyright_presence",
      "description": "作品著作权布尔标记为 1 或数量大于 0",
      "logic": {
        "op": "or",
        "rules": [
          {
            "op": "numeric_compare",
            "field": "has_work_copyright",
            "eq": 1
          },
          {
            "op": "numeric_compare",
            "field": "work_copyright_count",
            "gt": 0
          }
        ]
      }
    },
    "is_enabled": 1
  },
  {
    "company_tag_id": 135,
    "company_tag_name": "无作品著作权",
    "company_tag_subdimension_name": "作品著作权",
    "company_tag_auto_rule_type": "direct_match",
    "rule_definition": {
      "version": 1,
      "tag_name": "无作品著作权",
      "subdimension_name": "作品著作权",
      "exclusive_group": "work_copyright_presence",
      "description": "作品著作权布尔标记为 0 且数量为 0",
      "logic": {
        "op": "and",
        "rules": [
          {
            "op": "numeric_compare",
            "field": "has_work_copyright",
            "eq": 0
          },
          {
            "op": "numeric_compare",
            "field": "work_copyright_count",
            "eq": 0
          }
        ]
      }
    },
    "is_enabled": 1
  },
  {
    "company_tag_id": 136,
    "company_tag_name": "有软件著作权",
    "company_tag_subdimension_name": "软件著作权",
    "company_tag_auto_rule_type": "direct_match",
    "rule_definition": {
      "version": 1,
      "tag_name": "有软件著作权",
      "subdimension_name": "软件著作权",
      "exclusive_group": "software_copyright_presence",
      "description": "软件著作权布尔标记为 1 或数量大于 0",
      "logic": {
        "op": "or",
        "rules": [
          {
            "op": "numeric_compare",
            "field": "has_software_copyright",
            "eq": 1
          },
          {
            "op": "numeric_compare",
            "field": "software_copyright_count",
            "gt": 0
          }
        ]
      }
    },
    "is_enabled": 1
  },
  {
    "company_tag_id": 137,
    "company_tag_name": "无软件著作权",
    "company_tag_subdimension_name": "软件著作权",
    "company_tag_auto_rule_type": "direct_match",
    "rule_definition": {
      "version": 1,
      "tag_name": "无软件著作权",
      "subdimension_name": "软件著作权",
      "exclusive_group": "software_copyright_presence",
      "description": "软件著作权布尔标记为 0 且数量为 0",
      "logic": {
        "op": "and",
        "rules": [
          {
            "op": "numeric_compare",
            "field": "has_software_copyright",
            "eq": 0
          },
          {
            "op": "numeric_compare",
            "field": "software_copyright_count",
            "eq": 0
          }
        ]
      }
    },
    "is_enabled": 1
  },
  {
    "company_tag_id": 138,
    "company_tag_name": "是高新技术企业",
    "company_tag_subdimension_name": "高新技术企业",
    "company_tag_auto_rule_type": "direct_match",
    "rule_definition": {
      "version": 1,
      "tag_name": "是高新技术企业",
      "subdimension_name": "高新技术企业",
      "exclusive_group": "high_tech_enterprise",
      "description": "is_high_tech_enterprise = 1",
      "logic": {
        "op": "numeric_compare",
        "field": "is_high_tech_enterprise",
        "eq": 1
      }
    },
    "is_enabled": 1
  },
  {
    "company_tag_id": 139,
    "company_tag_name": "不是高新技术企业",
    "company_tag_subdimension_name": "高新技术企业",
    "company_tag_auto_rule_type": "direct_match",
    "rule_definition": {
      "version": 1,
      "tag_name": "不是高新技术企业",
      "subdimension_name": "高新技术企业",
      "exclusive_group": "high_tech_enterprise",
      "description": "is_high_tech_enterprise = 0",
      "logic": {
        "op": "numeric_compare",
        "field": "is_high_tech_enterprise",
        "eq": 0
      }
    },
    "is_enabled": 1
  },
  {
    "company_tag_id": 150,
    "company_tag_name": "有失信被执行",
    "company_tag_subdimension_name": "失信被执行",
    "company_tag_auto_rule_type": "direct_match",
    "rule_definition": {
      "version": 1,
      "tag_name": "有失信被执行",
      "subdimension_name": "失信被执行",
      "exclusive_group": "risk_dishonest_execution",
      "description": "失信被执行布尔标记为 1 或数量大于 0",
      "logic": {
        "op": "or",
        "rules": [
          {
            "op": "numeric_compare",
            "field": "has_dishonest_execution",
            "eq": 1
          },
          {
            "op": "numeric_compare",
            "field": "dishonest_execution_count",
            "gt": 0
          }
        ]
      }
    },
    "is_enabled": 1
  },
  {
    "company_tag_id": 151,
    "company_tag_name": "无失信被执行",
    "company_tag_subdimension_name": "失信被执行",
    "company_tag_auto_rule_type": "direct_match",
    "rule_definition": {
      "version": 1,
      "tag_name": "无失信被执行",
      "subdimension_name": "失信被执行",
      "exclusive_group": "risk_dishonest_execution",
      "description": "失信被执行布尔标记为 0 且数量为 0",
      "logic": {
        "op": "and",
        "rules": [
          {
            "op": "numeric_compare",
            "field": "has_dishonest_execution",
            "eq": 0
          },
          {
            "op": "numeric_compare",
            "field": "dishonest_execution_count",
            "eq": 0
          }
        ]
      }
    },
    "is_enabled": 1
  },
  {
    "company_tag_id": 152,
    "company_tag_name": "有动产抵押",
    "company_tag_subdimension_name": "动产抵押",
    "company_tag_auto_rule_type": "direct_match",
    "rule_definition": {
      "version": 1,
      "tag_name": "有动产抵押",
      "subdimension_name": "动产抵押",
      "exclusive_group": "risk_chattel_mortgage",
      "description": "动产抵押布尔标记为 1 或数量大于 0",
      "logic": {
        "op": "or",
        "rules": [
          {
            "op": "numeric_compare",
            "field": "has_chattel_mortgage",
            "eq": 1
          },
          {
            "op": "numeric_compare",
            "field": "chattel_mortgage_count",
            "gt": 0
          }
        ]
      }
    },
    "is_enabled": 1
  },
  {
    "company_tag_id": 153,
    "company_tag_name": "无动产抵押",
    "company_tag_subdimension_name": "动产抵押",
    "company_tag_auto_rule_type": "direct_match",
    "rule_definition": {
      "version": 1,
      "tag_name": "无动产抵押",
      "subdimension_name": "动产抵押",
      "exclusive_group": "risk_chattel_mortgage",
      "description": "动产抵押布尔标记为 0 且数量为 0",
      "logic": {
        "op": "and",
        "rules": [
          {
            "op": "numeric_compare",
            "field": "has_chattel_mortgage",
            "eq": 0
          },
          {
            "op": "numeric_compare",
            "field": "chattel_mortgage_count",
            "eq": 0
          }
        ]
      }
    },
    "is_enabled": 1
  },
  {
    "company_tag_id": 154,
    "company_tag_name": "有经营异常",
    "company_tag_subdimension_name": "经营异常",
    "company_tag_auto_rule_type": "direct_match",
    "rule_definition": {
      "version": 1,
      "tag_name": "有经营异常",
      "subdimension_name": "经营异常",
      "exclusive_group": "risk_business_abnormal",
      "description": "经营异常布尔标记为 1 或数量大于 0",
      "logic": {
        "op": "or",
        "rules": [
          {
            "op": "numeric_compare",
            "field": "has_business_abnormal",
            "eq": 1
          },
          {
            "op": "numeric_compare",
            "field": "business_abnormal_count",
            "gt": 0
          }
        ]
      }
    },
    "is_enabled": 1
  },
  {
    "company_tag_id": 155,
    "company_tag_name": "无经营异常",
    "company_tag_subdimension_name": "经营异常",
    "company_tag_auto_rule_type": "direct_match",
    "rule_definition": {
      "version": 1,
      "tag_name": "无经营异常",
      "subdimension_name": "经营异常",
      "exclusive_group": "risk_business_abnormal",
      "description": "经营异常布尔标记为 0 且数量为 0",
      "logic": {
        "op": "and",
        "rules": [
          {
            "op": "numeric_compare",
            "field": "has_business_abnormal",
            "eq": 0
          },
          {
            "op": "numeric_compare",
            "field": "business_abnormal_count",
            "eq": 0
          }
        ]
      }
    },
    "is_enabled": 1
  },
  {
    "company_tag_id": 156,
    "company_tag_name": "有法律文书",
    "company_tag_subdimension_name": "法律文书",
    "company_tag_auto_rule_type": "direct_match",
    "rule_definition": {
      "version": 1,
      "tag_name": "有法律文书",
      "subdimension_name": "法律文书",
      "exclusive_group": "risk_legal_document",
      "description": "法律文书布尔标记为 1 或数量大于 0",
      "logic": {
        "op": "or",
        "rules": [
          {
            "op": "numeric_compare",
            "field": "has_legal_document",
            "eq": 1
          },
          {
            "op": "numeric_compare",
            "field": "legal_doc_all_count",
            "gt": 0
          }
        ]
      }
    },
    "is_enabled": 1
  },
  {
    "company_tag_id": 157,
    "company_tag_name": "无法律文书",
    "company_tag_subdimension_name": "法律文书",
    "company_tag_auto_rule_type": "direct_match",
    "rule_definition": {
      "version": 1,
      "tag_name": "无法律文书",
      "subdimension_name": "法律文书",
      "exclusive_group": "risk_legal_document",
      "description": "法律文书布尔标记为 0 且数量为 0",
      "logic": {
        "op": "and",
        "rules": [
          {
            "op": "numeric_compare",
            "field": "has_legal_document",
            "eq": 0
          },
          {
            "op": "numeric_compare",
            "field": "legal_doc_all_count",
            "eq": 0
          }
        ]
      }
    },
    "is_enabled": 1
  },
  {
    "company_tag_id": 158,
    "company_tag_name": "有行政处罚",
    "company_tag_subdimension_name": "行政处罚",
    "company_tag_auto_rule_type": "direct_match",
    "rule_definition": {
      "version": 1,
      "tag_name": "有行政处罚",
      "subdimension_name": "行政处罚",
      "exclusive_group": "risk_admin_penalty",
      "description": "行政处罚布尔标记为 1 或数量大于 0",
      "logic": {
        "op": "or",
        "rules": [
          {
            "op": "numeric_compare",
            "field": "has_admin_penalty",
            "eq": 1
          },
          {
            "op": "numeric_compare",
            "field": "admin_penalty_count",
            "gt": 0
          }
        ]
      }
    },
    "is_enabled": 1
  },
  {
    "company_tag_id": 159,
    "company_tag_name": "无行政处罚",
    "company_tag_subdimension_name": "行政处罚",
    "company_tag_auto_rule_type": "direct_match",
    "rule_definition": {
      "version": 1,
      "tag_name": "无行政处罚",
      "subdimension_name": "行政处罚",
      "exclusive_group": "risk_admin_penalty",
      "description": "行政处罚布尔标记为 0 且数量为 0",
      "logic": {
        "op": "and",
        "rules": [
          {
            "op": "numeric_compare",
            "field": "has_admin_penalty",
            "eq": 0
          },
          {
            "op": "numeric_compare",
            "field": "admin_penalty_count",
            "eq": 0
          }
        ]
      }
    },
    "is_enabled": 1
  },
  {
    "company_tag_id": 160,
    "company_tag_name": "有破产重叠",
    "company_tag_subdimension_name": "破产重叠",
    "company_tag_auto_rule_type": "direct_match",
    "rule_definition": {
      "version": 1,
      "tag_name": "有破产重叠",
      "subdimension_name": "破产重叠",
      "exclusive_group": "risk_bankruptcy_overlap",
      "description": "破产重叠布尔标记为 1 或数量大于 0",
      "logic": {
        "op": "or",
        "rules": [
          {
            "op": "numeric_compare",
            "field": "has_bankruptcy_overlap",
            "eq": 1
          },
          {
            "op": "numeric_compare",
            "field": "bankruptcy_overlap_count",
            "gt": 0
          }
        ]
      }
    },
    "is_enabled": 1
  },
  {
    "company_tag_id": 161,
    "company_tag_name": "无破产重叠",
    "company_tag_subdimension_name": "破产重叠",
    "company_tag_auto_rule_type": "direct_match",
    "rule_definition": {
      "version": 1,
      "tag_name": "无破产重叠",
      "subdimension_name": "破产重叠",
      "exclusive_group": "risk_bankruptcy_overlap",
      "description": "破产重叠布尔标记为 0 且数量为 0",
      "logic": {
        "op": "and",
        "rules": [
          {
            "op": "numeric_compare",
            "field": "has_bankruptcy_overlap",
            "eq": 0
          },
          {
            "op": "numeric_compare",
            "field": "bankruptcy_overlap_count",
            "eq": 0
          }
        ]
      }
    },
    "is_enabled": 1
  },
  {
    "company_tag_id": 164,
    "company_tag_name": "有环保处罚",
    "company_tag_subdimension_name": "环保处罚",
    "company_tag_auto_rule_type": "direct_match",
    "rule_definition": {
      "version": 1,
      "tag_name": "有环保处罚",
      "subdimension_name": "环保处罚",
      "exclusive_group": "risk_env_penalty",
      "description": "环保处罚布尔标记为 1 或数量大于 0",
      "logic": {
        "op": "or",
        "rules": [
          {
            "op": "numeric_compare",
            "field": "has_env_penalty",
            "eq": 1
          },
          {
            "op": "numeric_compare",
            "field": "env_penalty_count",
            "gt": 0
          }
        ]
      }
    },
    "is_enabled": 1
  },
  {
    "company_tag_id": 165,
    "company_tag_name": "无环保处罚",
    "company_tag_subdimension_name": "环保处罚",
    "company_tag_auto_rule_type": "direct_match",
    "rule_definition": {
      "version": 1,
      "tag_name": "无环保处罚",
      "subdimension_name": "环保处罚",
      "exclusive_group": "risk_env_penalty",
      "description": "环保处罚布尔标记为 0 且数量为 0",
      "logic": {
        "op": "and",
        "rules": [
          {
            "op": "numeric_compare",
            "field": "has_env_penalty",
            "eq": 0
          },
          {
            "op": "numeric_compare",
            "field": "env_penalty_count",
            "eq": 0
          }
        ]
      }
    },
    "is_enabled": 1
  },
  {
    "company_tag_id": 166,
    "company_tag_name": "有股权冻结",
    "company_tag_subdimension_name": "股权冻结",
    "company_tag_auto_rule_type": "direct_match",
    "rule_definition": {
      "version": 1,
      "tag_name": "有股权冻结",
      "subdimension_name": "股权冻结",
      "exclusive_group": "risk_equity_freeze",
      "description": "股权冻结布尔标记为 1 或数量大于 0",
      "logic": {
        "op": "or",
        "rules": [
          {
            "op": "numeric_compare",
            "field": "has_equity_freeze",
            "eq": 1
          },
          {
            "op": "numeric_compare",
            "field": "equity_freeze_count",
            "gt": 0
          }
        ]
      }
    },
    "is_enabled": 1
  },
  {
    "company_tag_id": 167,
    "company_tag_name": "无股权冻结",
    "company_tag_subdimension_name": "股权冻结",
    "company_tag_auto_rule_type": "direct_match",
    "rule_definition": {
      "version": 1,
      "tag_name": "无股权冻结",
      "subdimension_name": "股权冻结",
      "exclusive_group": "risk_equity_freeze",
      "description": "股权冻结布尔标记为 0 且数量为 0",
      "logic": {
        "op": "and",
        "rules": [
          {
            "op": "numeric_compare",
            "field": "has_equity_freeze",
            "eq": 0
          },
          {
            "op": "numeric_compare",
            "field": "equity_freeze_count",
            "eq": 0
          }
        ]
      }
    },
    "is_enabled": 1
  },
  {
    "company_tag_id": 168,
    "company_tag_name": "有被执行人",
    "company_tag_subdimension_name": "被执行人",
    "company_tag_auto_rule_type": "direct_match",
    "rule_definition": {
      "version": 1,
      "tag_name": "有被执行人",
      "subdimension_name": "被执行人",
      "exclusive_group": "risk_executed_person",
      "description": "被执行人布尔标记为 1 或数量大于 0",
      "logic": {
        "op": "or",
        "rules": [
          {
            "op": "numeric_compare",
            "field": "has_executed_person",
            "eq": 1
          },
          {
            "op": "numeric_compare",
            "field": "executed_person_count",
            "gt": 0
          }
        ]
      }
    },
    "is_enabled": 1
  },
  {
    "company_tag_id": 169,
    "company_tag_name": "无被执行人",
    "company_tag_subdimension_name": "被执行人",
    "company_tag_auto_rule_type": "direct_match",
    "rule_definition": {
      "version": 1,
      "tag_name": "无被执行人",
      "subdimension_name": "被执行人",
      "exclusive_group": "risk_executed_person",
      "description": "被执行人布尔标记为 0 且数量为 0",
      "logic": {
        "op": "and",
        "rules": [
          {
            "op": "numeric_compare",
            "field": "has_executed_person",
            "eq": 0
          },
          {
            "op": "numeric_compare",
            "field": "executed_person_count",
            "eq": 0
          }
        ]
      }
    },
    "is_enabled": 1
  }
]
